igapy/__init__.py
igapy/accounts.py
igapy/cli.py
igapy/client.py
igapy/costs.py
igapy/exceptions.py
igapy/history.py
igapy/markets.py
igapy/operations.py
igapy/orders.py
igapy/prices.py
igapy/repeat.py
igapy/sentiment.py
igapy/session.py
igapy/streaming.py
igapy/utils.py
igapy/watchlists.py
igapy-1.0.1.dist-info/licenses/LICENSE
igapy-1.0.1.dist-info/METADATA
igapy-1.0.1.dist-info/WHEEL
igapy-1.0.1.dist-info/entry_points.txt
igapy-1.0.1.dist-info/top_level.txt
igapy-1.0.1.dist-info/RECORD
