Metadata-Version: 2.4
Name: igapy
Version: 1.0.1
Summary: A modern Python wrapper for the IG REST and streaming API.
Author-email: Vilhelm Hilding <hi@vilhelmhilding.com>
License: MIT License
Project-URL: Homepage, https://github.com/vilhelmhilding/igapy
Project-URL: Source, https://github.com/vilhelmhilding/igapy
Classifier: License :: OSI Approved :: MIT License
Classifier: Programming Language :: Python :: 3
Classifier: Programming Language :: Python :: 3.11
Classifier: Programming Language :: Python :: 3.12
Classifier: Operating System :: OS Independent
Requires-Python: >=3.11
License-File: LICENSE
Requires-Dist: requests
Requires-Dist: websocket-client
Requires-Dist: lightstreamer-client-lib
Provides-Extra: dev
Requires-Dist: pytest; extra == "dev"
Requires-Dist: flake8; extra == "dev"
Requires-Dist: black; extra == "dev"
Requires-Dist: pytest-cov; extra == "dev"
Dynamic: license-file
